audio_program_generator/__init__.py
audio_program_generator/__main__.py
audio_program_generator/apg.py
audio_program_generator-1.12.1.dist-info/LICENSE
audio_program_generator-1.12.1.dist-info/WHEEL
audio_program_generator-1.12.1.dist-info/entry_points.txt
audio_program_generator-1.12.1.dist-info/METADATA
audio_program_generator-1.12.1.dist-info/RECORD
