Metadata-Version: 2.1
Name: audio-program-generator
Version: 1.12.1
Summary: Create an audio program from a text file containing English sentences
Home-page: https://github.com/jeffwright13/audio_program_generator/
License: MIT
Author: Jeff Wright
Author-email: jeff.washcloth@gmail.com
Requires-Python: >=3.7,<3.10
Classifier: License :: OSI Approved :: MIT License
Classifier: Programming Language :: Python :: 3
Classifier: Programming Language :: Python :: 3.7
Classifier: Programming Language :: Python :: 3.8
Classifier: Programming Language :: Python :: 3.9
Requires-Dist: alive-progress (>=2.1.0,<3.0.0)
Requires-Dist: gTTS (>=2.2.2,<3.0.0)
Requires-Dist: pydub (>=0.25.1,<0.26.0)
Requires-Dist: sentence-splitter (>=1.4,<2.0)
Requires-Dist: single-source (>=0.2.0,<0.3.0)
Requires-Dist: typer (>=0.4.0,<0.5.0)
Project-URL: Repository, https://github.com/jeffwright13/audio_program_generator/
